os_ryu/__init__.py
os_ryu-0.0.1.dist-info/METADATA
os_ryu-0.0.1.dist-info/RECORD
os_ryu-0.0.1.dist-info/WHEEL
os_ryu-0.0.1.dist-info/top_level.txt
